{
  "statusBarOrder": [],
  "ribbonBarOrder": [],
  "fileExplorerOrder": {
    "": [
      "1. Daily",
      "회사",
      "4. Yealry",
      "Project",
      "내가 풀은 알고리즘",
      "알아두면 쓸데 없는 코딩지식",
      "영어",
      "옵시디언 사용법",
      "일상",
      "자기 소개 사이트",
      "자료구조",
      "키보드",
      "템플릿",
      "API",
      "Attached file",
      "Back End",
      "Chrome",
      "DATABASE",
      "Excalidraw",
      "Front End",
      "Git",
      "Github",
      "L3 Study",
      "Server",
      "Tags",
      "Travel",
      "OIP.jpg",
      "README.md",
      "Docker",
      "이력서에 적을만한것"
    ]
  },
  "actionBarOrder": {},
  "autoHide": false,
  "autoHideDelay": 2000,
  "dragDelay": 200,
  "sortOrder": "custom",
  "useCollapse": true
}